{"updated": "2026-07-18 11:56:17", "updated_ts": 1784343377, "scan_sec": 180, "us_open": false, "ws": true, "liq_events": 65568, "count": 35, "cols": ["흡수/이탈", "VWAP", "MTF", "오더북", "청산", "볼밴", "스퀴즈", "ATR", "레인지", "FLOW", "SURGE", "KIMCHI"], "rows": [{"sym": "SYNUSDT", "base": "SYN", "mark": "💎", "why": "초입(-0%) + 강한연료 — 노다지", "alpha": 100, "g": [["흡수/이탈", "ACC +28", 28], ["VWAP", "VWAP 강한 돌파 +10", 10], ["MTF", "BTC 대비 초강세 +12", 12], ["오더북", "매도 우위 ×0.85 -4", -4], ["청산", "↑ 숏청산 우위 $87K +5", 5], ["볼밴", "상단 접근 +6", 6], ["스퀴즈", "정상 +0", 0], ["ATR", "고변동성 -4", -4], ["레인지", "레인지 상단 +6", 6], ["FLOW", "Flow -2", -2], ["SURGE", "×4.80 +18", 18], ["KIMCHI", "—", 0]], "conflict": ["매도벽"], "onchain": null, "price": 0.2252, "p24": -0.44, "oi4": 11.5, "oi1": 2.3, "cvd": 0.799, "fr": 0.005, "atr": 16.36, "flow": -1.1, "surge": 4.8, "ret4": 19.24, "bb_pos": 0.849, "bb_squeeze": false, "bb_just_broke": false, "rng": 0.767, "kimp": null, "liq": [87173.2652064, 43342.8865766, 156], "vwap_broke": false, "spot_fuel": false, "turnover": 71091298, "tradfi": false, "pinned": false, "rank": 1, "since": 1784336537, "since_min": 114}, {"sym": "ZETAUSDT", "base": "ZETA", "mark": "🟢", "why": "초입(+6%) + 연료 — 진입검토", "alpha": 100, "g": [["흡수/이탈", "ACC +14", 14], ["VWAP", "VWAP 위 지지 +4", 4], ["MTF", "BTC 동조화 +0", 0], ["오더북", "매수벽 우위 ×1.88 +8", 8], ["청산", "미미 $1K 0", 0], ["볼밴", "밴드 중단 0", 0], ["스퀴즈", "정상 +0", 0], ["ATR", "정상 변동성 +0", 0], ["레인지", "레인지 상단 +6", 6], ["FLOW", "Flow +48", 48], ["SURGE", "×0.53 +0", 0], ["KIMCHI", "+0.68%", 0]], "conflict": [], "onchain": null, "price": 0.03531, "p24": 5.91, "oi4": 6.3, "oi1": 0.2, "cvd": 0.709, "fr": 0.005, "atr": 2.41, "flow": 64.5, "surge": 0.53, "ret4": 0.31, "bb_pos": 0.744, "bb_squeeze": false, "bb_just_broke": false, "rng": 0.683, "kimp": 0.68, "liq": [0, 802.8501200000001, 2], "vwap_broke": false, "spot_fuel": false, "turnover": 20396608, "tradfi": false, "pinned": false, "rank": 2, "since": 1784340137, "since_min": 54}, {"sym": "AVAAIUSDT", "base": "AVAAI", "mark": "🟢", "why": "연료생존 — 진입검토", "alpha": 70, "g": [["흡수/이탈", "— 0", 0], ["VWAP", "VWAP 강한 돌파 +10", 10], ["MTF", "BTC 대비 강세 +6", 6], ["오더북", "균형 ×0.91 +0", 0], ["청산", "미미 $16K 0", 0], ["볼밴", "압축+상단 — 돌파임박 ★ +12", 12], ["스퀴즈", "정상 +0", 0], ["ATR", "정상 변동성 +0", 0], ["레인지", "레인지 상단 +6", 6], ["FLOW", "Flow +2", 2], ["SURGE", "×1.73 +4", 4], ["KIMCHI", "—", 0]], "conflict": ["이미 +29%"], "onchain": null, "price": 0.007882, "p24": 28.79, "oi4": 4.9, "oi1": -0.4, "cvd": 0.661, "fr": 0.0237, "atr": 4.53, "flow": 1.0, "surge": 1.73, "ret4": 4.26, "bb_pos": 0.887, "bb_squeeze": true, "bb_just_broke": false, "rng": 0.905, "kimp": null, "liq": [16267.4075775, 5903.3573099, 70], "vwap_broke": false, "spot_fuel": false, "turnover": 22253466, "tradfi": false, "pinned": false, "rank": 3, "since": 1784341757, "since_min": 26}, {"sym": "BANKUSDT", "base": "BANK", "mark": "🟢", "why": "연료생존 — 진입검토", "alpha": 66, "g": [["흡수/이탈", "— 0", 0], ["VWAP", "VWAP 강한 돌파 +10", 10], ["MTF", "BTC 대비 초강세 +12", 12], ["오더북", "균형 ×0.94 +0", 0], ["청산", "↑ 숏청산 우위 $210K +5", 5], ["볼밴", "밴드압축 40.0% — 대기 +4", 4], ["스퀴즈", "정상 +0", 0], ["ATR", "고변동성 -4", -4], ["레인지", "레인지 상단 +6", 6], ["FLOW", "Flow +3", 3], ["SURGE", "×0.65 +0", 0], ["KIMCHI", "—", 0]], "conflict": ["이미 +22%"], "onchain": null, "price": 0.07613, "p24": 22.49, "oi4": 3.5, "oi1": 2.7, "cvd": 0.715, "fr": 0.0095, "atr": 10.41, "flow": 2.1, "surge": 0.65, "ret4": 13.23, "bb_pos": 0.717, "bb_squeeze": true, "bb_just_broke": false, "rng": 0.692, "kimp": null, "liq": [210132.1200287, 92023.2116503, 423], "vwap_broke": false, "spot_fuel": false, "turnover": 458841562, "tradfi": false, "pinned": false, "rank": 4, "since": 1784340137, "since_min": 54}, {"sym": "TUSDT", "base": "T", "mark": "🟡", "why": "연료 약함 — 관찰", "alpha": 87, "g": [["흡수/이탈", "ACC +14", 14], ["VWAP", "VWAP 강한 돌파 +10", 10], ["MTF", "BTC 대비 강세 +6", 6], ["오더북", "균형 ×1.10 +0", 0], ["청산", "미미 $13K 0", 0], ["볼밴", "압축 뚫고 나감 — 초입 ★ +10", 10], ["스퀴즈", "대형 FR스퀴즈 ★ +8", 8], ["ATR", "정상 변동성 +0", 0], ["레인지", "레인지 내 0", 0], ["FLOW", "Flow +1", 1], ["SURGE", "×2.15 +8", 8], ["KIMCHI", "+3.24%", 0]], "conflict": [], "onchain": null, "price": 0.004291, "p24": 7.54, "oi4": 6.5, "oi1": 2.2, "cvd": 0.456, "fr": -0.2869, "atr": 4.69, "flow": 0.6, "surge": 2.15, "ret4": 4.22, "bb_pos": 1.021, "bb_squeeze": true, "bb_just_broke": true, "rng": 0.467, "kimp": 3.24, "liq": [12924.7802051, 13316.9621787, 45], "vwap_broke": false, "spot_fuel": false, "turnover": 72720926, "tradfi": false, "pinned": false, "rank": 5, "since": 1784343377, "since_min": 0}, {"sym": "OPUSDT", "base": "OP", "mark": "🟡", "why": "연료 약함 — 관찰", "alpha": 79, "g": [["흡수/이탈", "— 0", 0], ["VWAP", "VWAP 위 지지 +4", 4], ["MTF", "BTC 동조화 +0", 0], ["오더북", "매수 우위 ×1.36 +4", 4], ["청산", "미미 $1K 0", 0], ["볼밴", "압축+상단 — 돌파임박 ★ +12", 12], ["스퀴즈", "정상 +0", 0], ["ATR", "낮은 변동성 +3", 3], ["레인지", "레인지 상단 +6", 6], ["FLOW", "Flow +16", 16], ["SURGE", "×1.56 +4", 4], ["KIMCHI", "+0.40%", 0]], "conflict": [], "onchain": null, "price": 0.0973, "p24": -0.1, "oi4": 2.0, "oi1": 0.9, "cvd": 1.0, "fr": -0.0007, "atr": 1.35, "flow": 9.9, "surge": 1.56, "ret4": 1.57, "bb_pos": 0.88, "bb_squeeze": true, "bb_just_broke": false, "rng": 0.615, "kimp": 0.4, "liq": [1168.79811, 0, 1], "vwap_broke": false, "spot_fuel": false, "turnover": 21072083, "tradfi": false, "pinned": false, "rank": 6, "since": 1784164651, "since_min": 2978}, {"sym": "AVAXUSDT", "base": "AVAX", "mark": "🟡", "why": "연료 약함 — 관찰", "alpha": 77, "g": [["흡수/이탈", "— 0", 0], ["VWAP", "VWAP 위 지지 +4", 4], ["MTF", "BTC 동조화 +0", 0], ["오더북", "매수 우위 ×1.30 +4", 4], ["청산", "청산 데이터 없음 0", 0], ["볼밴", "상단 접근 +6", 6], ["스퀴즈", "정상 +0", 0], ["ATR", "극저 변동성 +6", 6], ["레인지", "레인지 상단 +6", 6], ["FLOW", "Flow +21", 21], ["SURGE", "×0.52 +0", 0], ["KIMCHI", "+0.22%", 0]], "conflict": [], "onchain": null, "price": 6.624, "p24": 2.52, "oi4": 0.5, "oi1": 0.5, "cvd": 1.0, "fr": 0.0089, "atr": 0.62, "flow": 12.8, "surge": 0.52, "ret4": 1.01, "bb_pos": 0.875, "bb_squeeze": false, "bb_just_broke": false, "rng": 0.915, "kimp": 0.22, "liq": null, "vwap_broke": false, "spot_fuel": false, "turnover": 57478248, "tradfi": false, "pinned": false, "rank": 7, "since": 1784163032, "since_min": 3005}, {"sym": "ADAUSDT", "base": "ADA", "mark": "🟡", "why": "연료 약함 — 관찰", "alpha": 76, "g": [["흡수/이탈", "— 0", 0], ["VWAP", "VWAP 위 지지 +4", 4], ["MTF", "BTC 동조화 +0", 0], ["오더북", "균형 ×1.14 +0", 0], ["청산", "↑ 숏청산 우위 $62K +5", 5], ["볼밴", "상단 접근 +6", 6], ["스퀴즈", "정상 +0", 0], ["ATR", "낮은 변동성 +3", 3], ["레인지", "레인지 상단 +6", 6], ["FLOW", "Flow +22", 22], ["SURGE", "×0.72 +0", 0], ["KIMCHI", "+0.25%", 0]], "conflict": [], "onchain": null, "price": 0.1685, "p24": 5.84, "oi4": 1.8, "oi1": 0.4, "cvd": 0.866, "fr": 0.01, "atr": 1.06, "flow": 13.9, "surge": 0.72, "ret4": 1.69, "bb_pos": 0.883, "bb_squeeze": false, "bb_just_broke": false, "rng": 0.94, "kimp": 0.25, "liq": [61903.47387, 5.3888, 17], "vwap_broke": false, "spot_fuel": false, "turnover": 164495429, "tradfi": false, "pinned": false, "rank": 8, "since": 1784333153, "since_min": 170}, {"sym": "INJUSDT", "base": "INJ", "mark": "🟡", "why": "연료 약함 — 관찰", "alpha": 71, "g": [["흡수/이탈", "— 0", 0], ["VWAP", "VWAP 위 지지 +4", 4], ["MTF", "BTC 대비 강세 +6", 6], ["오더북", "균형 ×1.13 +0", 0], ["청산", "미미 $8K 0", 0], ["볼밴", "상단 접근 +6", 6], ["스퀴즈", "FR스퀴즈 중 +5", 5], ["ATR", "낮은 변동성 +3", 3], ["레인지", "레인지 상단 +6", 6], ["FLOW", "Flow +7", 7], ["SURGE", "×1.66 +4", 4], ["KIMCHI", "+0.21%", 0]], "conflict": [], "onchain": null, "price": 5.186, "p24": 7.17, "oi4": 1.1, "oi1": -0.2, "cvd": 0.592, "fr": -0.0136, "atr": 1.28, "flow": 4.1, "surge": 1.66, "ret4": 2.07, "bb_pos": 0.868, "bb_squeeze": false, "bb_just_broke": false, "rng": 0.936, "kimp": 0.21, "liq": [8080.7942995, 759.9673, 10], "vwap_broke": false, "spot_fuel": false, "turnover": 34604768, "tradfi": false, "pinned": false, "rank": 9, "since": 1784343377, "since_min": 0}, {"sym": "ESPORTSUSDT", "base": "ESPORTS", "mark": "🟡", "why": "연료 약함 — 관찰", "alpha": 67, "g": [["흡수/이탈", "— 0", 0], ["VWAP", "VWAP 강한 돌파 +10", 10], ["MTF", "BTC 대비 초강세 +12", 12], ["오더북", "매도벽 압박 ×0.49 -8", -8], ["청산", "대형 숏청산 ★ $383K +8", 8], ["볼밴", "상단 접근 +6", 6], ["스퀴즈", "롱 과열 -4", -4], ["ATR", "고변동성 -4", -4], ["레인지", "레인지 상단 +6", 6], ["FLOW", "Flow +7", 7], ["SURGE", "×1.78 +4", 4], ["KIMCHI", "—", 0]], "conflict": [], "onchain": null, "price": 0.0336, "p24": 38.61, "oi4": 2.6, "oi1": -1.5, "cvd": 0.755, "fr": 0.055, "atr": 17.37, "flow": 4.2, "surge": 1.78, "ret4": 35.55, "bb_pos": 0.991, "bb_squeeze": false, "bb_just_broke": false, "rng": 0.759, "kimp": null, "liq": [383422.7371474, 43914.1218507, 290], "vwap_broke": false, "spot_fuel": false, "turnover": 267661206, "tradfi": false, "pinned": false, "rank": 10, "since": 1784340137, "since_min": 54}, {"sym": "VVVUSDT", "base": "VVV", "mark": "🟡", "why": "연료 약함 — 관찰", "alpha": 67, "g": [["흡수/이탈", "— 0", 0], ["VWAP", "VWAP 위 지지 +4", 4], ["MTF", "BTC 대비 강세 +6", 6], ["오더북", "매도 우위 ×0.85 -4", -4], ["청산", "미미 $11K 0", 0], ["볼밴", "상단 접근 +6", 6], ["스퀴즈", "정상 +0", 0], ["ATR", "낮은 변동성 +3", 3], ["레인지", "레인지 상단 +6", 6], ["FLOW", "Flow +16", 16], ["SURGE", "×0.56 +0", 0], ["KIMCHI", "+0.03%", 0]], "conflict": [], "onchain": null, "price": 11.448, "p24": 6.29, "oi4": 0.7, "oi1": 0.4, "cvd": 1.0, "fr": 0.005, "atr": 1.85, "flow": 9.9, "surge": 0.56, "ret4": 2.45, "bb_pos": 0.854, "bb_squeeze": false, "bb_just_broke": false, "rng": 0.941, "kimp": 0.03, "liq": [10890.06348805, 257.07024, 12], "vwap_broke": false, "spot_fuel": false, "turnover": 28422878, "tradfi": false, "pinned": false, "rank": 11, "since": 1784307737, "since_min": 594}, {"sym": "SOLUSDT", "base": "SOL", "mark": "🟡", "why": "연료 약함 — 관찰", "alpha": 63, "g": [["흡수/이탈", "— 0", 0], ["VWAP", "VWAP 위 지지 +4", 4], ["MTF", "BTC 동조화 +0", 0], ["오더북", "균형 ×1.05 +0", 0], ["청산", "미미 $30K 0", 0], ["볼밴", "밴드압축 1.7% — 대기 +4", 4], ["스퀴즈", "정상 +0", 0], ["ATR", "극저 변동성 +6", 6], ["레인지", "레인지 상단 +6", 6], ["FLOW", "Flow +13", 13], ["SURGE", "×0.37 +0", 0], ["KIMCHI", "+0.11%", 0]], "conflict": [], "onchain": null, "price": 75.22, "p24": 0.56, "oi4": 0.4, "oi1": 0.1, "cvd": 1.0, "fr": -0.0006, "atr": 0.36, "flow": 8.3, "surge": 0.37, "ret4": 0.32, "bb_pos": 0.795, "bb_squeeze": true, "bb_just_broke": false, "rng": 0.841, "kimp": 0.11, "liq": [29954.545100000003, 118.5329, 14], "vwap_broke": false, "spot_fuel": false, "turnover": 1018687432, "tradfi": false, "pinned": true, "rank": 12, "since": 1784095877, "since_min": 4125}, {"sym": "LINKUSDT", "base": "LINK", "mark": "🟡", "why": "연료 약함 — 관찰", "alpha": 61, "g": [["흡수/이탈", "— 0", 0], ["VWAP", "VWAP 위 지지 +4", 4], ["MTF", "BTC 동조화 +0", 0], ["오더북", "균형 ×1.06 +0", 0], ["청산", "미미 $2K 0", 0], ["볼밴", "압축+상단 — 돌파임박 ★ +12", 12], ["스퀴즈", "정상 +0", 0], ["ATR", "극저 변동성 +6", 6], ["레인지", "레인지 상단 +6", 6], ["FLOW", "Flow +3", 3], ["SURGE", "×0.52 +0", 0], ["KIMCHI", "+0.08%", 0]], "conflict": [], "onchain": {"src": "cold", "score": 73, "mark": "🟢", "grade": "강한 펌프 가능성", "cold_score": 73, "cold_usd": 10252334, "cold_n": 6, "cold_wallets": 6, "cold_days": 29.6, "peak": 10.9, "accum_score": null, "accum_usd": null, "accum_wallets": null, "accum_wd": null, "accum_days": null, "conc": false}, "price": 8.27, "p24": 0.21, "oi4": -0.5, "oi1": -0.1, "cvd": 0.785, "fr": 0.0028, "atr": 0.47, "flow": 2.0, "surge": 0.52, "ret4": 0.38, "bb_pos": 0.836, "bb_squeeze": true, "bb_just_broke": false, "rng": 0.82, "kimp": 0.08, "liq": [2242.54428, 0, 2], "vwap_broke": false, "spot_fuel": false, "turnover": 76365989, "tradfi": false, "pinned": true, "rank": 13, "since": 1784112298, "since_min": 3851}, {"sym": "LTCUSDT", "base": "LTC", "mark": "🟡", "why": "연료 약함 — 관찰", "alpha": 59, "g": [["흡수/이탈", "— 0", 0], ["VWAP", "VWAP 위 지지 +4", 4], ["MTF", "BTC 동조화 +0", 0], ["오더북", "균형 ×1.00 +0", 0], ["청산", "미미 $3K 0", 0], ["볼밴", "방금 상단 돌파 — 초입 +8", 8], ["스퀴즈", "정상 +0", 0], ["ATR", "극저 변동성 +6", 6], ["레인지", "레인지 상단 +6", 6], ["FLOW", "Flow +5", 5], ["SURGE", "×1.08 +0", 0], ["KIMCHI", "—", 0]], "conflict": [], "onchain": null, "price": 45.52, "p24": 1.47, "oi4": 0.6, "oi1": 0.3, "cvd": 0.794, "fr": -0.0018, "atr": 0.52, "flow": 3.0, "surge": 1.08, "ret4": 1.07, "bb_pos": 1.024, "bb_squeeze": false, "bb_just_broke": true, "rng": 0.799, "kimp": null, "liq": [3003.59226, 655.96652, 5], "vwap_broke": false, "spot_fuel": false, "turnover": 61064075, "tradfi": false, "pinned": false, "rank": 14, "since": 1784340317, "since_min": 50}, {"sym": "ONDOUSDT", "base": "ONDO", "mark": "🟡", "why": "연료 약함 — 관찰", "alpha": 57, "g": [["흡수/이탈", "— 0", 0], ["VWAP", "VWAP 아래 저항 -4", -4], ["MTF", "BTC 동조화 +0", 0], ["오더북", "균형 ×1.12 +0", 0], ["청산", "↑ 숏청산 우위 $39K +5", 5], ["볼밴", "밴드압축 5.1% — 대기 +4", 4], ["스퀴즈", "정상 +0", 0], ["ATR", "정상 변동성 +0", 0], ["레인지", "레인지 상단 +6", 6], ["FLOW", "Flow +16", 16], ["SURGE", "×1.21 +0", 0], ["KIMCHI", "-0.03%", 0]], "conflict": [], "onchain": null, "price": 0.3773, "p24": 3.12, "oi4": 1.4, "oi1": 0.3, "cvd": 0.818, "fr": 0.0015, "atr": 2.08, "flow": 10.0, "surge": 1.21, "ret4": 1.95, "bb_pos": 0.671, "bb_squeeze": true, "bb_just_broke": false, "rng": 0.625, "kimp": -0.03, "liq": [38533.959282230004, 315.97188, 21], "vwap_broke": true, "spot_fuel": false, "turnover": 123644835, "tradfi": false, "pinned": false, "rank": 15, "since": 1784217932, "since_min": 2090}, {"sym": "ZECUSDT", "base": "ZEC", "mark": "🟡", "why": "연료 약함 — 관찰", "alpha": 56, "g": [["흡수/이탈", "— 0", 0], ["VWAP", "VWAP 위 지지 +4", 4], ["MTF", "BTC 동조화 +0", 0], ["오더북", "매수벽 우위 ×1.62 +8", 8], ["청산", "↓ 롱청산 우위 $42K -6", -6], ["볼밴", "밴드압축 4.7% — 대기 +4", 4], ["스퀴즈", "정상 +0", 0], ["ATR", "낮은 변동성 +3", 3], ["레인지", "레인지 상단 +6", 6], ["FLOW", "Flow +7", 7], ["SURGE", "×0.51 +0", 0], ["KIMCHI", "—", 0]], "conflict": [], "onchain": null, "price": 546.11, "p24": 3.62, "oi4": 0.5, "oi1": 0.1, "cvd": 0.565, "fr": 0.0071, "atr": 1.02, "flow": 4.4, "surge": 0.51, "ret4": 0.67, "bb_pos": 0.7, "bb_squeeze": true, "bb_just_broke": false, "rng": 0.693, "kimp": null, "liq": [12763.93083, 41688.7809, 32], "vwap_broke": false, "spot_fuel": false, "turnover": 619597694, "tradfi": false, "pinned": false, "rank": 16, "since": 1784314937, "since_min": 474}, {"sym": "VIRTUALUSDT", "base": "VIRTUAL", "mark": "🟡", "why": "연료 약함 — 관찰", "alpha": 54, "g": [["흡수/이탈", "— 0", 0], ["VWAP", "VWAP 위 지지 +4", 4], ["MTF", "BTC 대비 강세 +6", 6], ["오더북", "균형 ×1.09 +0", 0], ["청산", "미미 $0K 0", 0], ["볼밴", "밴드압축 5.5% — 대기 +4", 4], ["스퀴즈", "정상 +0", 0], ["ATR", "낮은 변동성 +3", 3], ["레인지", "레인지 상단 +6", 6], ["FLOW", "Flow +1", 1], ["SURGE", "×1.24 +0", 0], ["KIMCHI", "+0.11%", 0]], "conflict": [], "onchain": null, "price": 0.6384, "p24": 4.08, "oi4": 2.1, "oi1": 0.7, "cvd": 0.558, "fr": -0.0097, "atr": 1.74, "flow": 0.4, "surge": 1.24, "ret4": 2.39, "bb_pos": 0.761, "bb_squeeze": true, "bb_just_broke": false, "rng": 0.73, "kimp": 0.11, "liq": [37.83582, 0, 1], "vwap_broke": false, "spot_fuel": false, "turnover": 25052664, "tradfi": false, "pinned": false, "rank": 17, "since": 1784304137, "since_min": 654}, {"sym": "SUIUSDT", "base": "SUI", "mark": "🟡", "why": "연료 약함 — 관찰", "alpha": 52, "g": [["흡수/이탈", "— 0", 0], ["VWAP", "VWAP 위 지지 +4", 4], ["MTF", "BTC 동조화 +0", 0], ["오더북", "균형 ×1.00 +0", 0], ["청산", "미미 $2K 0", 0], ["볼밴", "밴드압축 2.1% — 대기 +4", 4], ["스퀴즈", "정상 +0", 0], ["ATR", "극저 변동성 +6", 6], ["레인지", "레인지 상단 +6", 6], ["FLOW", "Flow +2", 2], ["SURGE", "×0.38 +0", 0], ["KIMCHI", "+0.12%", 0]], "conflict": [], "onchain": null, "price": 0.7406, "p24": 0.27, "oi4": 0.7, "oi1": 0.1, "cvd": 0.411, "fr": 0.0052, "atr": 0.45, "flow": 1.2, "surge": 0.38, "ret4": 0.27, "bb_pos": 0.794, "bb_squeeze": true, "bb_just_broke": false, "rng": 0.727, "kimp": 0.12, "liq": [0, 1752.4336, 1], "vwap_broke": false, "spot_fuel": false, "turnover": 96740548, "tradfi": false, "pinned": false, "rank": 18, "since": 1784275336, "since_min": 1134}, {"sym": "ETHUSDT", "base": "ETH", "mark": "🟡", "why": "연료 약함 — 관찰", "alpha": 46, "g": [["흡수/이탈", "— 0", 0], ["VWAP", "VWAP 위 지지 +4", 4], ["MTF", "BTC 동조화 +0", 0], ["오더북", "매도벽 압박 ×0.39 -8", -8], ["청산", "혼조 0", 0], ["볼밴", "밴드압축 1.5% — 대기 +4", 4], ["스퀴즈", "정상 +0", 0], ["ATR", "극저 변동성 +6", 6], ["레인지", "레인지 상단 +6", 6], ["FLOW", "Flow +4", 4], ["SURGE", "×0.28 +0", 0], ["KIMCHI", "+0.22%", 0]], "conflict": [], "onchain": null, "price": 1841.32, "p24": -0.12, "oi4": 0.0, "oi1": 0.0, "cvd": 0.483, "fr": 0.0032, "atr": 0.33, "flow": 2.5, "surge": 0.28, "ret4": 0.12, "bb_pos": 0.69, "bb_squeeze": true, "bb_just_broke": false, "rng": 0.683, "kimp": 0.22, "liq": [182368.50882000002, 139072.97698, 48], "vwap_broke": false, "spot_fuel": false, "turnover": 6900966182, "tradfi": false, "pinned": true, "rank": 19, "since": 1784203517, "since_min": 2331}, {"sym": "BTCUSDT", "base": "BTC", "mark": "🟡", "why": "연료 약함 — 관찰", "alpha": 45, "g": [["흡수/이탈", "— 0", 0], ["VWAP", "VWAP 위 지지 +4", 4], ["MTF", "BTC 동조화 +0", 0], ["오더북", "매수벽 우위 ×3.17 +8", 8], ["청산", "↓ 롱청산 우위 $349K -6", -6], ["볼밴", "밴드 중단 0", 0], ["스퀴즈", "정상 +0", 0], ["ATR", "극저 변동성 +6", 6], ["레인지", "레인지 상단 +6", 6], ["FLOW", "Flow -3", -3], ["SURGE", "×0.22 +0", 0], ["KIMCHI", "+0.11%", 0]], "conflict": [], "onchain": null, "price": 63926.9, "p24": 0.89, "oi4": 0.3, "oi1": 0.1, "cvd": 0.233, "fr": 0.0075, "atr": 0.19, "flow": -2.2, "surge": 0.22, "ret4": -0.04, "bb_pos": 0.687, "bb_squeeze": false, "bb_just_broke": false, "rng": 0.768, "kimp": 0.11, "liq": [35170.5599, 348853.7157, 25], "vwap_broke": false, "spot_fuel": false, "turnover": 9497390942, "tradfi": false, "pinned": true, "rank": 20, "since": 1784131378, "since_min": 3533}, {"sym": "1000BONKUSDT", "base": "BONK", "mark": "🟡", "why": "연료 약함 — 관찰", "alpha": 43, "g": [["흡수/이탈", "— 0", 0], ["VWAP", "VWAP 아래 저항 -4", -4], ["MTF", "BTC 동조화 +0", 0], ["오더북", "균형 ×1.15 +0", 0], ["청산", "↑ 숏청산 우위 $74K +5", 5], ["볼밴", "밴드 중단 0", 0], ["스퀴즈", "대형 FR스퀴즈 ★ +8", 8], ["ATR", "정상 변동성 +0", 0], ["레인지", "레인지 내 0", 0], ["FLOW", "Flow +0", 0], ["SURGE", "×1.45 +4", 4], ["KIMCHI", "-99.79%", 0]], "conflict": [], "onchain": null, "price": 0.003101, "p24": -7.93, "oi4": 2.5, "oi1": -0.1, "cvd": 0.488, "fr": -0.0911, "atr": 2.27, "flow": 0.1, "surge": 1.45, "ret4": 0.85, "bb_pos": 0.202, "bb_squeeze": false, "bb_just_broke": false, "rng": 0.197, "kimp": -99.79, "liq": [73942.662109, 802.8057741, 14], "vwap_broke": true, "spot_fuel": false, "turnover": 45169761, "tradfi": false, "pinned": false, "rank": 21, "since": 1784340137, "since_min": 54}, {"sym": "SNXXUSDT", "base": "SNXX", "mark": "🟡", "why": "연료 약함 — 관찰", "alpha": 41, "g": [["흡수/이탈", "— 0", 0], ["VWAP", "VWAP 아래 저항 -4", -4], ["MTF", "BTC 동조화 +0", 0], ["오더북", "매수 우위 ×1.23 +4", 4], ["청산", "미미 $0K 0", 0], ["볼밴", "밴드압축 28.5% — 대기 +4", 4], ["스퀴즈", "정상 +0", 0], ["ATR", "낮은 변동성 +3", 3], ["레인지", "레인지 내 0", 0], ["FLOW", "Flow +4", 4], ["SURGE", "×0.16 +0", 0], ["KIMCHI", "—", 0]], "conflict": [], "onchain": null, "price": 12.86, "p24": -3.24, "oi4": 2.6, "oi1": -3.6, "cvd": 0.793, "fr": 0.0162, "atr": 1.83, "flow": 2.8, "surge": 0.16, "ret4": 0.63, "bb_pos": 0.279, "bb_squeeze": true, "bb_just_broke": false, "rng": 0.141, "kimp": null, "liq": [7.650199999999999, 470.9613637, 3], "vwap_broke": true, "spot_fuel": false, "turnover": 102588429, "tradfi": false, "pinned": false, "rank": 22, "since": 1784340317, "since_min": 50}, {"sym": "REUSDT", "base": "RE", "mark": "🟡", "why": "연료 약함 — 관찰", "alpha": 41, "g": [["흡수/이탈", "— 0", 0], ["VWAP", "VWAP 아래 저항 -4", -4], ["MTF", "BTC 동조화 +0", 0], ["오더북", "균형 ×1.02 +0", 0], ["청산", "미미 $3K 0", 0], ["볼밴", "밴드압축 5.7% — 대기 +4", 4], ["스퀴즈", "대형 FR스퀴즈 ★ +8", 8], ["ATR", "낮은 변동성 +3", 3], ["레인지", "레인지 내 0", 0], ["FLOW", "Flow +0", 0], ["SURGE", "×0.86 +0", 0], ["KIMCHI", "+0.16%", 0]], "conflict": [], "onchain": null, "price": 0.443, "p24": -5.71, "oi4": 2.2, "oi1": 0.7, "cvd": 0.471, "fr": -0.0698, "atr": 1.66, "flow": 0.0, "surge": 0.86, "ret4": -0.58, "bb_pos": 0.302, "bb_squeeze": true, "bb_just_broke": false, "rng": 0.166, "kimp": 0.16, "liq": [3254.0224512, 3207.0848443, 22], "vwap_broke": true, "spot_fuel": false, "turnover": 34181394, "tradfi": false, "pinned": false, "rank": 23, "since": 1784326277, "since_min": 284}, {"sym": "AEROUSDT", "base": "AERO", "mark": "🟡", "why": "연료 약함 — 관찰", "alpha": 37, "g": [["흡수/이탈", "— 0", 0], ["VWAP", "VWAP 강한 돌파 +10", 10], ["MTF", "BTC 동조화 +0", 0], ["오더북", "매수 우위 ×1.30 +4", 4], ["청산", "미미 $8K 0", 0], ["볼밴", "밴드 중단 0", 0], ["스퀴즈", "FR스퀴즈 중 +5", 5], ["ATR", "정상 변동성 +0", 0], ["레인지", "레인지 내 0", 0], ["FLOW", "Flow -12", -12], ["SURGE", "×0.65 +0", 0], ["KIMCHI", "+0.25%", 0]], "conflict": [], "onchain": null, "price": 0.4764, "p24": 0.42, "oi4": 3.0, "oi1": 0.8, "cvd": 0.429, "fr": -0.0256, "atr": 2.15, "flow": -7.3, "surge": 0.65, "ret4": 1.47, "bb_pos": 0.332, "bb_squeeze": false, "bb_just_broke": false, "rng": 0.219, "kimp": 0.25, "liq": [0, 8116.52056592, 12], "vwap_broke": false, "spot_fuel": false, "turnover": 44310232, "tradfi": false, "pinned": false, "rank": 24, "since": 1784286136, "since_min": 954}, {"sym": "STARUSDT", "base": "STAR", "mark": "🟡", "why": "연료 약함 — 관찰", "alpha": 37, "g": [["흡수/이탈", "— 0", 0], ["VWAP", "VWAP 아래 저항 -4", -4], ["MTF", "BTC 동조화 +0", 0], ["오더북", "매도벽 압박 ×0.34 -8", -8], ["청산", "미미 $1K 0", 0], ["볼밴", "밴드압축 29.0% — 대기 +4", 4], ["스퀴즈", "정상 +0", 0], ["ATR", "정상 변동성 +0", 0], ["레인지", "레인지 상단 +6", 6], ["FLOW", "Flow +9", 9], ["SURGE", "×1.10 +0", 0], ["KIMCHI", "—", 0]], "conflict": [], "onchain": null, "price": 0.2263, "p24": 26.11, "oi4": 2.7, "oi1": -0.3, "cvd": 0.682, "fr": 0.0173, "atr": 3.63, "flow": 5.8, "surge": 1.1, "ret4": 1.38, "bb_pos": 0.734, "bb_squeeze": true, "bb_just_broke": false, "rng": 0.879, "kimp": null, "liq": [572.883982, 0, 5], "vwap_broke": true, "spot_fuel": false, "turnover": 24814992, "tradfi": false, "pinned": false, "rank": 25, "since": 1784340137, "since_min": 54}, {"sym": "ARBUSDT", "base": "ARB", "mark": "🟡", "why": "연료 약함 — 관찰", "alpha": 37, "g": [["흡수/이탈", "— 0", 0], ["VWAP", "VWAP 아래 저항 -4", -4], ["MTF", "BTC 동조화 +0", 0], ["오더북", "매수 우위 ×1.18 +4", 4], ["청산", "↑ 숏청산 우위 $49K +5", 5], ["볼밴", "밴드 중단 0", 0], ["스퀴즈", "정상 +0", 0], ["ATR", "낮은 변동성 +3", 3], ["레인지", "레인지 내 0", 0], ["FLOW", "Flow -1", -1], ["SURGE", "×0.92 +0", 0], ["KIMCHI", "+0.46%", 0]], "conflict": [], "onchain": null, "price": 0.09049, "p24": 2.32, "oi4": 1.0, "oi1": 0.6, "cvd": 0.722, "fr": 0.01, "atr": 1.66, "flow": -0.7, "surge": 0.92, "ret4": 0.03, "bb_pos": 0.702, "bb_squeeze": false, "bb_just_broke": false, "rng": 0.594, "kimp": 0.46, "liq": [48658.5259051, 1999.4008383999999, 13], "vwap_broke": true, "spot_fuel": false, "turnover": 39446712, "tradfi": false, "pinned": false, "rank": 26, "since": 1784318717, "since_min": 411}, {"sym": "DOTUSDT", "base": "DOT", "mark": "🟡", "why": "연료 약함 — 관찰", "alpha": 36, "g": [["흡수/이탈", "— 0", 0], ["VWAP", "VWAP 아래 저항 -4", -4], ["MTF", "BTC 동조화 +0", 0], ["오더북", "매수 우위 ×1.25 +4", 4], ["청산", "미미 $1K 0", 0], ["볼밴", "밴드압축 1.8% — 대기 +4", 4], ["스퀴즈", "정상 +0", 0], ["ATR", "극저 변동성 +6", 6], ["레인지", "레인지 내 0", 0], ["FLOW", "Flow -4", -4], ["SURGE", "×0.38 +0", 0], ["KIMCHI", "+0.20%", 0]], "conflict": [], "onchain": null, "price": 0.847, "p24": -0.7, "oi4": 1.3, "oi1": -0.0, "cvd": 0.589, "fr": -0.0026, "atr": 0.53, "flow": -2.5, "surge": 0.38, "ret4": -0.24, "bb_pos": 0.287, "bb_squeeze": true, "bb_just_broke": false, "rng": 0.424, "kimp": 0.2, "liq": [0, 795.0878, 2], "vwap_broke": true, "spot_fuel": false, "turnover": 50093828, "tradfi": false, "pinned": false, "rank": 27, "since": 1784296937, "since_min": 774}, {"sym": "QQQUSDT", "base": "QQQ", "mark": "🟡", "why": "연료 약함 — 관찰", "alpha": 36, "g": [["흡수/이탈", "— 0", 0], ["VWAP", "VWAP 위 지지 +4", 4], ["MTF", "BTC 동조화 +0", 0], ["오더북", "매수벽 우위 ×1.74 +8", 8], ["청산", "청산 데이터 없음 0", 0], ["볼밴", "밴드압축 1.2% — 대기 +4", 4], ["스퀴즈", "정상 +0", 0], ["ATR", "극저 변동성 +6", 6], ["레인지", "레인지 내 0", 0], ["FLOW", "Flow -16", -16], ["SURGE", "×0.21 +0", 0], ["KIMCHI", "—", 0]], "conflict": [], "onchain": null, "price": 695.76, "p24": -0.49, "oi4": 0.9, "oi1": -0.1, "cvd": 0.693, "fr": 0.0, "atr": 0.13, "flow": -10.3, "surge": 0.21, "ret4": 0.04, "bb_pos": 0.482, "bb_squeeze": true, "bb_just_broke": false, "rng": 0.542, "kimp": null, "liq": null, "vwap_broke": false, "spot_fuel": false, "turnover": 215310828, "tradfi": true, "pinned": false, "rank": 28, "since": 1784307737, "since_min": 594}, {"sym": "LABUSDT", "base": "LAB", "mark": "🟡", "why": "연료 약함 — 관찰", "alpha": 29, "g": [["흡수/이탈", "— 0", 0], ["VWAP", "VWAP 아래 저항 -4", -4], ["MTF", "BTC 동조화 +0", 0], ["오더북", "매수 우위 ×1.46 +4", 4], ["청산", "미미 $7K 0", 0], ["볼밴", "밴드압축 10.0% — 대기 +4", 4], ["스퀴즈", "정상 +0", 0], ["ATR", "정상 변동성 +0", 0], ["레인지", "레인지 내 0", 0], ["FLOW", "Flow -5", -5], ["SURGE", "×0.77 +0", 0], ["KIMCHI", "—", 0]], "conflict": [], "onchain": null, "price": 0.1821, "p24": -8.26, "oi4": 3.0, "oi1": 1.3, "cvd": 0.383, "fr": 0.0329, "atr": 3.64, "flow": -3.2, "surge": 0.77, "ret4": -3.39, "bb_pos": 0.288, "bb_squeeze": true, "bb_just_broke": false, "rng": 0.263, "kimp": null, "liq": [41.6165, 6624.5809472, 31], "vwap_broke": true, "spot_fuel": false, "turnover": 133064846, "tradfi": false, "pinned": false, "rank": 29, "since": 1784340677, "since_min": 44}, {"sym": "TQQQUSDT", "base": "TQQQ", "mark": "🟡", "why": "연료 약함 — 관찰", "alpha": 26, "g": [["흡수/이탈", "— 0", 0], ["VWAP", "VWAP 위 지지 +4", 4], ["MTF", "BTC 동조화 +0", 0], ["오더북", "매도벽 압박 ×0.67 -8", -8], ["청산", "청산 데이터 없음 0", 0], ["볼밴", "밴드압축 3.7% — 대기 +4", 4], ["스퀴즈", "정상 +0", 0], ["ATR", "극저 변동성 +6", 6], ["레인지", "레인지 내 0", 0], ["FLOW", "Flow -10", -10], ["SURGE", "×0.11 +0", 0], ["KIMCHI", "—", 0]], "conflict": [], "onchain": null, "price": 67.61, "p24": -1.4, "oi4": 0.5, "oi1": 0.2, "cvd": 0.717, "fr": 0.0256, "atr": 0.55, "flow": -6.2, "surge": 0.11, "ret4": 0.21, "bb_pos": 0.51, "bb_squeeze": true, "bb_just_broke": false, "rng": 0.563, "kimp": null, "liq": null, "vwap_broke": false, "spot_fuel": false, "turnover": 26510106, "tradfi": true, "pinned": false, "rank": 30, "since": 1784322136, "since_min": 354}, {"sym": "FILUSDT", "base": "FIL", "mark": "🟡", "why": "연료 약함 — 관찰", "alpha": 23, "g": [["흡수/이탈", "— 0", 0], ["VWAP", "VWAP 위 지지 +4", 4], ["MTF", "BTC 동조화 +0", 0], ["오더북", "균형 ×1.02 +0", 0], ["청산", "미미 $0K 0", 0], ["볼밴", "밴드압축 1.5% — 대기 +4", 4], ["스퀴즈", "정상 +0", 0], ["ATR", "극저 변동성 +6", 6], ["레인지", "레인지 내 0", 0], ["FLOW", "Flow -21", -21], ["SURGE", "×0.30 +0", 0], ["KIMCHI", "+0.10%", 0]], "conflict": [], "onchain": null, "price": 0.7645, "p24": -0.33, "oi4": 0.5, "oi1": 0.1, "cvd": 0.794, "fr": 0.01, "atr": 0.44, "flow": -13.2, "surge": 0.3, "ret4": 0.18, "bb_pos": 0.459, "bb_squeeze": true, "bb_just_broke": false, "rng": 0.497, "kimp": 0.1, "liq": [0, 0.45858, 1], "vwap_broke": false, "spot_fuel": false, "turnover": 31842483, "tradfi": false, "pinned": false, "rank": 31, "since": 1784293517, "since_min": 830}, {"sym": "AAVEUSDT", "base": "AAVE", "mark": "🟡", "why": "연료 약함 — 관찰", "alpha": 1, "g": [["흡수/이탈", "— 0", 0], ["VWAP", "VWAP 아래 저항 -4", -4], ["MTF", "BTC 동조화 +0", 0], ["오더북", "균형 ×1.12 +0", 0], ["청산", "미미 $6K 0", 0], ["볼밴", "밴드 하단 -3", -3], ["스퀴즈", "정상 +0", 0], ["ATR", "극저 변동성 +6", 6], ["레인지", "저점 근접 -6", -6], ["FLOW", "Flow -22", -22], ["SURGE", "×0.91 +0", 0], ["KIMCHI", "+0.14%", 0]], "conflict": [], "onchain": null, "price": 89.36, "p24": -0.95, "oi4": 1.4, "oi1": 0.5, "cvd": 0.0, "fr": 0.0088, "atr": 0.66, "flow": -14.0, "surge": 0.91, "ret4": -0.84, "bb_pos": -0.055, "bb_squeeze": false, "bb_just_broke": false, "rng": 0.043, "kimp": 0.14, "liq": [80.676, 6193.6533, 10], "vwap_broke": true, "spot_fuel": false, "turnover": 60580407, "tradfi": false, "pinned": false, "rank": 32, "since": 1784170952, "since_min": 2873}, {"sym": "TIAUSDT", "base": "TIA", "mark": "🟡", "why": "연료 약함 — 관찰", "alpha": 0, "g": [["흡수/이탈", "— 0", 0], ["VWAP", "VWAP 아래 저항 -4", -4], ["MTF", "BTC 동조화 +0", 0], ["오더북", "매도 우위 ×0.84 -4", -4], ["청산", "↓ 롱청산 우위 $132K -6", -6], ["볼밴", "밴드 하단 -3", -3], ["스퀴즈", "정상 +0", 0], ["ATR", "낮은 변동성 +3", 3], ["레인지", "저점 근접 -6", -6], ["FLOW", "Flow -27", -27], ["SURGE", "×1.01 +0", 0], ["KIMCHI", "+0.15%", 0]], "conflict": [], "onchain": null, "price": 0.3685, "p24": -3.21, "oi4": 1.2, "oi1": -0.2, "cvd": 0.126, "fr": -0.0014, "atr": 1.3, "flow": -17.0, "surge": 1.01, "ret4": -2.18, "bb_pos": -0.077, "bb_squeeze": false, "bb_just_broke": false, "rng": 0.086, "kimp": 0.15, "liq": [0, 132001.6073948, 19], "vwap_broke": true, "spot_fuel": false, "turnover": 26581567, "tradfi": false, "pinned": false, "rank": 33, "since": 1784322136, "since_min": 354}, {"sym": "BILLUSDT", "base": "BILL", "mark": "🔴", "why": "하락 중 -15% — 롱 근거 없음", "alpha": 32, "g": [["흡수/이탈", "— 0", 0], ["VWAP", "VWAP 아래 저항 -4", -4], ["MTF", "BTC 대비 약세 -6", -6], ["오더북", "매수 우위 ×1.21 +4", 4], ["청산", "미미 $20K 0", 0], ["볼밴", "밴드압축 22.9% — 대기 +4", 4], ["스퀴즈", "대형 FR스퀴즈 ★ +8", 8], ["ATR", "정상 변동성 +0", 0], ["레인지", "저점 근접 -6", -6], ["FLOW", "Flow -2", -2], ["SURGE", "×1.44 +4", 4], ["KIMCHI", "—", 0]], "conflict": [], "onchain": {"src": "cold", "score": 73, "mark": "🟢", "grade": "강한 펌프 가능성", "cold_score": 73, "cold_usd": 33392242, "cold_n": 8, "cold_wallets": 3, "cold_days": 19.3, "peak": 0.2, "accum_score": null, "accum_usd": null, "accum_wallets": null, "accum_wd": null, "accum_days": null, "conc": false}, "price": 0.02232, "p24": -14.74, "oi4": 0.2, "oi1": 1.7, "cvd": 0.21, "fr": -0.0532, "atr": 4.1, "flow": -1.5, "surge": 1.44, "ret4": -4.78, "bb_pos": 0.17, "bb_squeeze": true, "bb_just_broke": false, "rng": 0.032, "kimp": null, "liq": [6061.9591979, 20408.5229231, 49], "vwap_broke": true, "spot_fuel": false, "turnover": 41862679, "tradfi": false, "pinned": true, "rank": 34, "since": 1784339597, "since_min": 62}, {"sym": "HOMEUSDT", "base": "HOME", "mark": "🔴", "why": "하락 중 -19% — 롱 근거 없음", "alpha": 26, "g": [["흡수/이탈", "— 0", 0], ["VWAP", "VWAP 아래 저항 -4", -4], ["MTF", "BTC 대비 약세 -6", -6], ["오더북", "매수 우위 ×1.39 +4", 4], ["청산", "미미 $27K 0", 0], ["볼밴", "밴드압축 10.2% — 대기 +4", 4], ["스퀴즈", "대형 FR스퀴즈 ★ +8", 8], ["ATR", "정상 변동성 +0", 0], ["레인지", "레인지 내 0", 0], ["FLOW", "Flow -10", -10], ["SURGE", "×0.72 +0", 0], ["KIMCHI", "—", 0]], "conflict": [], "onchain": null, "price": 0.00768, "p24": -19.24, "oi4": 1.9, "oi1": -0.3, "cvd": 0.0, "fr": -1.2216, "atr": 3.0, "flow": -6.3, "surge": 0.72, "ret4": -4.95, "bb_pos": 0.051, "bb_squeeze": true, "bb_just_broke": false, "rng": 0.146, "kimp": null, "liq": [7981.1585955, 27116.2821876, 83], "vwap_broke": true, "spot_fuel": false, "turnover": 134010543, "tradfi": false, "pinned": false, "rank": 35, "since": 1784216837, "since_min": 2109}]}