{"updated": "2026-07-18 22:50:18", "updated_ts": 1784382618, "scan_sec": 180, "us_open": false, "ws": true, "liq_events": 77816, "count": 35, "cols": ["흡수/이탈", "VWAP", "MTF", "오더북", "청산", "볼밴", "스퀴즈", "ATR", "레인지", "FLOW", "SURGE", "KIMCHI"], "rows": [{"sym": "AVAAIUSDT", "base": "AVAAI", "mark": "💎", "why": "순위권 + 강한연료 — 아직 갈 자리", "alpha": 53, "g": [["흡수/이탈", "— 0", 0], ["VWAP", "VWAP 강한 돌파 +10", 10], ["MTF", "BTC 대비 강세 +6", 6], ["오더북", "매도벽 압박 ×0.33 -8", -8], ["청산", "↑ 숏청산 우위 $99K +5", 5], ["볼밴", "상단 접근 +6", 6], ["스퀴즈", "롱 과열 -4", -4], ["ATR", "고변동성 -4", -4], ["레인지", "레인지 상단 +6", 6], ["FLOW", "Flow -2", -2], ["SURGE", "×2.92 +8", 8], ["KIMCHI", "—", 0]], "conflict": ["매도벽", "이미 +25%"], "onchain": null, "price": 0.00914, "p24": 25.38, "oi4": 25.0, "oi1": -1.1, "cvd": 0.615, "fr": 0.0691, "atr": 10.87, "flow": -1.2, "surge": 2.92, "ret4": 4.59, "bb_pos": 0.998, "bb_squeeze": false, "bb_just_broke": false, "rng": 0.789, "kimp": null, "liq": [98983.1958061, 50725.816836800004, 226], "vwap_broke": false, "spot_fuel": false, "turnover": 65287293, "tradfi": false, "pinned": false, "rank": 1, "since": 1784380637, "since_min": 33}, {"sym": "LINKUSDT", "base": "LINK", "mark": "⭐", "why": "현물주도 상승 — 실제 돈", "alpha": 48, "g": [["흡수/이탈", "— 0", 0], ["VWAP", "VWAP 아래 저항 -4", -4], ["MTF", "BTC 동조화 +0", 0], ["오더북", "매도 우위 ×0.76 -4", -4], ["청산", "미미 $1K 0", 0], ["볼밴", "밴드 중단 0", 0], ["스퀴즈", "정상 +0", 0], ["ATR", "극저 변동성 +6", 6], ["레인지", "레인지 상단 +6", 6], ["FLOW", "Flow +6", 6], ["SURGE", "×2.12 +8", 8], ["KIMCHI", "-0.08%", 0]], "conflict": ["VWAP 아래", "매도벽"], "onchain": {"src": "cold", "score": 70, "mark": "🟢", "grade": "강한 펌프 가능성", "cold_score": 70, "cold_usd": 10129267, "cold_n": 5, "cold_wallets": 6, "cold_days": 30.1, "peak": 10.9, "accum_score": null, "accum_usd": null, "accum_wallets": null, "accum_wd": null, "accum_days": null, "conc": false}, "price": 8.262, "p24": 2.47, "oi4": 0.0, "oi1": 0.1, "cvd": 0.795, "fr": -0.0004, "atr": 0.59, "flow": 3.6, "surge": 2.12, "ret4": 0.47, "bb_pos": 0.632, "bb_squeeze": false, "bb_just_broke": false, "rng": 0.766, "kimp": -0.08, "liq": [840.69133, 307.80346, 5], "vwap_broke": true, "spot_fuel": true, "turnover": 50118863, "tradfi": false, "pinned": true, "rank": 2, "since": 1784377578, "since_min": 84}, {"sym": "ENSUSDT", "base": "ENS", "mark": "🟢", "why": "초입(+0%) + 연료 — 진입검토", "alpha": 95, "g": [["흡수/이탈", "ACC +14", 14], ["VWAP", "VWAP 강한 돌파 +10", 10], ["MTF", "BTC 대비 강세 +6", 6], ["오더북", "매도 우위 ×0.77 -4", -4], ["청산", "미미 $1K 0", 0], ["볼밴", "압축+상단 — 돌파임박 ★ +12", 12], ["스퀴즈", "정상 +0", 0], ["ATR", "낮은 변동성 +3", 3], ["레인지", "레인지 상단 +6", 6], ["FLOW", "Flow +14", 14], ["SURGE", "×1.90 +4", 4], ["KIMCHI", "+0.14%", 0]], "conflict": ["매도벽"], "onchain": null, "price": 4.615, "p24": 0.22, "oi4": 5.1, "oi1": 0.9, "cvd": 1.0, "fr": 0.0008, "atr": 1.6, "flow": 9.0, "surge": 1.9, "ret4": 3.68, "bb_pos": 0.879, "bb_squeeze": true, "bb_just_broke": false, "rng": 0.697, "kimp": 0.14, "liq": [530.691, 29.5379, 5], "vwap_broke": false, "spot_fuel": false, "turnover": 16182993, "tradfi": false, "pinned": false, "rank": 3, "since": 1784376138, "since_min": 107}, {"sym": "ETHFIUSDT", "base": "ETHFI", "mark": "🟢", "why": "연료생존 — 진입검토", "alpha": 83, "g": [["흡수/이탈", "ACC +14", 14], ["VWAP", "VWAP 강한 돌파 +10", 10], ["MTF", "BTC 대비 강세 +6", 6], ["오더북", "매수 우위 ×1.26 +4", 4], ["청산", "미미 $14K 0", 0], ["볼밴", "밴드 밖 진행중 — 이미 감 0", 0], ["스퀴즈", "정상 +0", 0], ["ATR", "낮은 변동성 +3", 3], ["레인지", "고점 돌파 +4", 4], ["FLOW", "Flow -6", -6], ["SURGE", "×3.28 +18", 18], ["KIMCHI", "-0.03%", 0]], "conflict": ["볼밴 이미 감", "레인지 고점"], "onchain": null, "price": 0.4633, "p24": 11.66, "oi4": 5.1, "oi1": 0.5, "cvd": 0.744, "fr": 0.005, "atr": 1.81, "flow": -3.5, "surge": 3.28, "ret4": 2.82, "bb_pos": 1.1, "bb_squeeze": true, "bb_just_broke": false, "rng": 0.958, "kimp": -0.03, "liq": [14179.791855939999, 589.74302, 17], "vwap_broke": false, "spot_fuel": false, "turnover": 20736973, "tradfi": false, "pinned": false, "rank": 4, "since": 1784376138, "since_min": 107}, {"sym": "ALLOUSDT", "base": "ALLO", "mark": "🟢", "why": "연료생존 — 진입검토", "alpha": 73, "g": [["흡수/이탈", "— 0", 0], ["VWAP", "VWAP 강한 돌파 +10", 10], ["MTF", "BTC 대비 강세 +6", 6], ["오더북", "매수벽 우위 ×4.70 +8", 8], ["청산", "↑ 숏청산 우위 $40K +5", 5], ["볼밴", "밴드 밖 진행중 — 이미 감 0", 0], ["스퀴즈", "정상 +0", 0], ["ATR", "정상 변동성 +0", 0], ["레인지", "레인지 상단 +6", 6], ["FLOW", "Flow +0", 0], ["SURGE", "×2.42 +8", 8], ["KIMCHI", "—", 0]], "conflict": ["볼밴 이미 감", "이미 +15%"], "onchain": null, "price": 0.46153, "p24": 15.13, "oi4": 4.8, "oi1": 1.2, "cvd": 0.794, "fr": 0.005, "atr": 3.74, "flow": -0.1, "surge": 2.42, "ret4": 4.16, "bb_pos": 1.018, "bb_squeeze": false, "bb_just_broke": false, "rng": 0.933, "kimp": null, "liq": [39733.4260054, 3543.7461603, 67], "vwap_broke": false, "spot_fuel": false, "turnover": 45048289, "tradfi": false, "pinned": false, "rank": 5, "since": 1784372538, "since_min": 167}, {"sym": "TRUMPUSDT", "base": "TRUMP", "mark": "🟢", "why": "연료생존 — 진입검토", "alpha": 54, "g": [["흡수/이탈", "ACC +14", 14], ["VWAP", "VWAP 아래 저항 -4", -4], ["MTF", "BTC 동조화 +0", 0], ["오더북", "매수 우위 ×1.20 +4", 4], ["청산", "혼조 0", 0], ["볼밴", "밴드 중단 0", 0], ["스퀴즈", "정상 +0", 0], ["ATR", "정상 변동성 +0", 0], ["레인지", "레인지 상단 +6", 6], ["FLOW", "Flow +4", 4], ["SURGE", "×1.31 +0", 0], ["KIMCHI", "-0.06%", 0]], "conflict": ["VWAP 아래"], "onchain": null, "price": 1.648, "p24": 8.85, "oi4": 5.1, "oi1": -0.2, "cvd": 0.533, "fr": 0.0027, "atr": 2.56, "flow": 2.4, "surge": 1.31, "ret4": -0.66, "bb_pos": 0.699, "bb_squeeze": false, "bb_just_broke": false, "rng": 0.67, "kimp": -0.06, "liq": [70966.4949153, 61963.48515039, 89], "vwap_broke": true, "spot_fuel": false, "turnover": 104157253, "tradfi": false, "pinned": false, "rank": 6, "since": 1784372538, "since_min": 167}, {"sym": "MUUUSDT", "base": "MUU", "mark": "🟢", "why": "초입(+6%) + 연료 — 진입검토", "alpha": 34, "g": [["흡수/이탈", "ACC +28", 28], ["VWAP", "VWAP 위 지지 +4", 4], ["MTF", "BTC 동조화 +0", 0], ["오더북", "매도벽 압박 ×0.47 -8", -8], ["청산", "청산 데이터 없음 0", 0], ["볼밴", "밴드압축 6.0% — 대기 +4", 4], ["스퀴즈", "정상 +0", 0], ["ATR", "극저 변동성 +6", 6], ["레인지", "레인지 내 0", 0], ["FLOW", "Flow -30", -30], ["SURGE", "×1.06 +0", 0], ["KIMCHI", "—", 0]], "conflict": ["매도벽"], "onchain": null, "price": 26.96, "p24": 5.56, "oi4": 14.3, "oi1": 3.5, "cvd": 0.596, "fr": 0.0, "atr": 0.6, "flow": -22.3, "surge": 1.06, "ret4": 0.33, "bb_pos": 0.444, "bb_squeeze": true, "bb_just_broke": false, "rng": 0.104, "kimp": null, "liq": null, "vwap_broke": false, "spot_fuel": false, "turnover": 17920092, "tradfi": false, "pinned": false, "rank": 7, "since": 1784382078, "since_min": 9}, {"sym": "SOXSUSDT", "base": "SOXS", "mark": "🟢", "why": "연료생존 — 진입검토", "alpha": 24, "g": [["흡수/이탈", "— 0", 0], ["VWAP", "VWAP 아래 저항 -4", -4], ["MTF", "BTC 동조화 +0", 0], ["오더북", "균형 ×1.01 +0", 0], ["청산", "미미 $1K 0", 0], ["볼밴", "밴드압축 2.4% — 대기 +4", 4], ["스퀴즈", "정상 +0", 0], ["ATR", "극저 변동성 +6", 6], ["레인지", "레인지 상단 +6", 6], ["FLOW", "Flow -18", -18], ["SURGE", "×0.95 +0", 0], ["KIMCHI", "—", 0]], "conflict": ["VWAP 아래"], "onchain": null, "price": 55.28, "p24": -7.74, "oi4": 4.6, "oi1": 1.5, "cvd": 0.674, "fr": 0.0, "atr": 0.85, "flow": -11.4, "surge": 0.95, "ret4": 0.56, "bb_pos": 0.792, "bb_squeeze": true, "bb_just_broke": false, "rng": 0.644, "kimp": null, "liq": [191.47500000000002, 929.7611839, 3], "vwap_broke": true, "spot_fuel": false, "turnover": 28021786, "tradfi": true, "pinned": false, "rank": 8, "since": 1784381718, "since_min": 15}, {"sym": "ATHUSDT", "base": "ATH", "mark": "🟡", "why": "연료 약함 — 관찰", "alpha": 74, "g": [["흡수/이탈", "— 0", 0], ["VWAP", "VWAP 아래 저항 -4", -4], ["MTF", "BTC 동조화 +0", 0], ["오더북", "매도 우위 ×0.87 -4", -4], ["청산", "미미 $0K 0", 0], ["볼밴", "밴드 하단 -3", -3], ["스퀴즈", "정상 +0", 0], ["ATR", "낮은 변동성 +3", 3], ["레인지", "레인지 내 0", 0], ["FLOW", "Flow +48", 48], ["SURGE", "×1.91 +4", 4], ["KIMCHI", "-0.18%", 0]], "conflict": [], "onchain": null, "price": 0.004335, "p24": 0.7, "oi4": 2.1, "oi1": 0.4, "cvd": 0.238, "fr": 0.005, "atr": 1.25, "flow": 60.6, "surge": 1.91, "ret4": -1.63, "bb_pos": 0.027, "bb_squeeze": false, "bb_just_broke": false, "rng": 0.165, "kimp": -0.18, "liq": [0, 457.60529690000004, 3], "vwap_broke": true, "spot_fuel": false, "turnover": 14423569, "tradfi": false, "pinned": false, "rank": 9, "since": 1784382258, "since_min": 5}, {"sym": "1000XECUSDT", "base": "XEC", "mark": "🟡", "why": "연료 약함 — 관찰", "alpha": 64, "g": [["흡수/이탈", "— 0", 0], ["VWAP", "VWAP 아래 저항 -4", -4], ["MTF", "BTC 대비 초강세 +12", 12], ["오더북", "매도 우위 ×0.71 -4", -4], ["청산", "대형 숏청산 ★ $546K +8", 8], ["볼밴", "상단 접근 +6", 6], ["스퀴즈", "FR스퀴즈 중 +5", 5], ["ATR", "고변동성 -4", -4], ["레인지", "레인지 상단 +6", 6], ["FLOW", "Flow +5", 5], ["SURGE", "×1.89 +4", 4], ["KIMCHI", "-99.90%", 0]], "conflict": [], "onchain": null, "price": 0.009436, "p24": 17.95, "oi4": 16.0, "oi1": 5.4, "cvd": 0.483, "fr": -0.0303, "atr": 9.14, "flow": 3.1, "surge": 1.89, "ret4": 11.22, "bb_pos": 0.877, "bb_squeeze": false, "bb_just_broke": false, "rng": 0.673, "kimp": -99.9, "liq": [545783.8119467, 127002.54736, 478], "vwap_broke": true, "spot_fuel": false, "turnover": 301401103, "tradfi": false, "pinned": false, "rank": 10, "since": 1784381358, "since_min": 21}, {"sym": "LTCUSDT", "base": "LTC", "mark": "🟡", "why": "연료 약함 — 관찰", "alpha": 63, "g": [["흡수/이탈", "— 0", 0], ["VWAP", "VWAP 위 지지 +4", 4], ["MTF", "BTC 동조화 +0", 0], ["오더북", "균형 ×1.04 +0", 0], ["청산", "미미 $4K 0", 0], ["볼밴", "압축+상단 — 돌파임박 ★ +12", 12], ["스퀴즈", "정상 +0", 0], ["ATR", "극저 변동성 +6", 6], ["레인지", "레인지 상단 +6", 6], ["FLOW", "Flow +1", 1], ["SURGE", "×1.42 +4", 4], ["KIMCHI", "—", 0]], "conflict": [], "onchain": null, "price": 45.69, "p24": 3.02, "oi4": 2.0, "oi1": 0.7, "cvd": 0.828, "fr": 0.009, "atr": 0.48, "flow": 0.5, "surge": 1.42, "ret4": 0.62, "bb_pos": 0.899, "bb_squeeze": true, "bb_just_broke": false, "rng": 0.889, "kimp": null, "liq": [4241.15311, 120.34044999999999, 7], "vwap_broke": false, "spot_fuel": false, "turnover": 33965142, "tradfi": false, "pinned": false, "rank": 11, "since": 1784340317, "since_min": 705}, {"sym": "SAMSUNGUSDT", "base": "SAMSUNG", "mark": "🟡", "why": "연료 약함 — 관찰", "alpha": 59, "g": [["흡수/이탈", "— 0", 0], ["VWAP", "VWAP 위 지지 +4", 4], ["MTF", "BTC 동조화 +0", 0], ["오더북", "매수벽 우위 ×1.62 +8", 8], ["청산", "청산 데이터 없음 0", 0], ["볼밴", "밴드압축 3.0% — 대기 +4", 4], ["스퀴즈", "정상 +0", 0], ["ATR", "극저 변동성 +6", 6], ["레인지", "레인지 내 0", 0], ["FLOW", "Flow +3", 3], ["SURGE", "×1.46 +4", 4], ["KIMCHI", "—", 0]], "conflict": [], "onchain": null, "price": 167.46, "p24": 6.04, "oi4": 2.5, "oi1": 1.5, "cvd": 0.345, "fr": -0.001, "atr": 0.73, "flow": 2.0, "surge": 1.46, "ret4": -0.58, "bb_pos": 0.228, "bb_squeeze": true, "bb_just_broke": false, "rng": 0.401, "kimp": null, "liq": null, "vwap_broke": false, "spot_fuel": false, "turnover": 85074703, "tradfi": true, "pinned": false, "rank": 12, "since": 1784314937, "since_min": 1128}, {"sym": "BTCUSDT", "base": "BTC", "mark": "🟡", "why": "연료 약함 — 관찰", "alpha": 54, "g": [["흡수/이탈", "— 0", 0], ["VWAP", "VWAP 아래 저항 -4", -4], ["MTF", "BTC 동조화 +0", 0], ["오더북", "매도벽 압박 ×0.02 -8", -8], ["청산", "대형 숏청산 ★ $510K +8", 8], ["볼밴", "밴드압축 0.6% — 대기 +4", 4], ["스퀴즈", "정상 +0", 0], ["ATR", "극저 변동성 +6", 6], ["레인지", "레인지 상단 +6", 6], ["FLOW", "Flow +8", 8], ["SURGE", "×1.79 +4", 4], ["KIMCHI", "+0.03%", 0]], "conflict": [], "onchain": null, "price": 64011.5, "p24": 2.04, "oi4": 0.3, "oi1": 0.2, "cvd": 0.644, "fr": 0.0046, "atr": 0.24, "flow": 5.1, "surge": 1.79, "ret4": 0.1, "bb_pos": 0.556, "bb_squeeze": true, "bb_just_broke": false, "rng": 0.783, "kimp": 0.03, "liq": [509647.3935, 102926.5652, 58], "vwap_broke": true, "spot_fuel": false, "turnover": 5563494044, "tradfi": false, "pinned": true, "rank": 13, "since": 1784131378, "since_min": 4187}, {"sym": "CLUSDT", "base": "CL", "mark": "🟡", "why": "연료 약함 — 관찰", "alpha": 52, "g": [["흡수/이탈", "— 0", 0], ["VWAP", "VWAP 아래 저항 -4", -4], ["MTF", "BTC 동조화 +0", 0], ["오더북", "매도벽 압박 ×0.66 -8", -8], ["청산", "↑ 숏청산 우위 $79K +5", 5], ["볼밴", "압축+상단 — 돌파임박 ★ +12", 12], ["스퀴즈", "정상 +0", 0], ["ATR", "극저 변동성 +6", 6], ["레인지", "레인지 상단 +6", 6], ["FLOW", "Flow -3", -3], ["SURGE", "×2.07 +8", 8], ["KIMCHI", "—", 0]], "conflict": [], "onchain": null, "price": 82.55, "p24": 1.91, "oi4": 2.0, "oi1": 0.3, "cvd": 0.887, "fr": 0.0, "atr": 0.46, "flow": -2.0, "surge": 2.07, "ret4": 0.5, "bb_pos": 0.846, "bb_squeeze": true, "bb_just_broke": false, "rng": 0.893, "kimp": null, "liq": [78805.5495, 1340.3490000000002, 22], "vwap_broke": true, "spot_fuel": false, "turnover": 458583908, "tradfi": false, "pinned": false, "rank": 14, "since": 1784162671, "since_min": 3665}, {"sym": "DOTUSDT", "base": "DOT", "mark": "🟡", "why": "연료 약함 — 관찰", "alpha": 50, "g": [["흡수/이탈", "— 0", 0], ["VWAP", "VWAP 아래 저항 -4", -4], ["MTF", "BTC 동조화 +0", 0], ["오더북", "균형 ×1.09 +0", 0], ["청산", "미미 $2K 0", 0], ["볼밴", "밴드 하단 -3", -3], ["스퀴즈", "FR스퀴즈 중 +5", 5], ["ATR", "극저 변동성 +6", 6], ["레인지", "저점 근접 -6", -6], ["FLOW", "Flow +22", 22], ["SURGE", "×1.26 +0", 0], ["KIMCHI", "+0.32%", 0]], "conflict": [], "onchain": null, "price": 0.833, "p24": -0.48, "oi4": 2.9, "oi1": 1.7, "cvd": 0.179, "fr": -0.015, "atr": 0.48, "flow": 14.1, "surge": 1.26, "ret4": -0.36, "bb_pos": 0.044, "bb_squeeze": false, "bb_just_broke": false, "rng": 0.032, "kimp": 0.32, "liq": [0, 2412.5053999999996, 6], "vwap_broke": true, "spot_fuel": false, "turnover": 35013008, "tradfi": false, "pinned": false, "rank": 15, "since": 1784296937, "since_min": 1428}, {"sym": "BILLUSDT", "base": "BILL", "mark": "🟡", "why": "연료 약함 — 관찰", "alpha": 48, "g": [["흡수/이탈", "— 0", 0], ["VWAP", "VWAP 위 지지 +4", 4], ["MTF", "BTC 대비 강세 +6", 6], ["오더북", "매도 우위 ×0.83 -4", -4], ["청산", "미미 $7K 0", 0], ["볼밴", "밴드압축 9.8% — 대기 +4", 4], ["스퀴즈", "FR스퀴즈 중 +5", 5], ["ATR", "정상 변동성 +0", 0], ["레인지", "레인지 내 0", 0], ["FLOW", "Flow +3", 3], ["SURGE", "×1.06 +0", 0], ["KIMCHI", "—", 0]], "conflict": [], "onchain": {"src": "cold", "score": 73, "mark": "🟢", "grade": "강한 펌프 가능성", "cold_score": 73, "cold_usd": 33392242, "cold_n": 8, "cold_wallets": 3, "cold_days": 19.7, "peak": 0.2, "accum_score": null, "accum_usd": null, "accum_wallets": null, "accum_wd": null, "accum_days": null, "conc": false}, "price": 0.02374, "p24": -6.5, "oi4": -1.8, "oi1": -1.4, "cvd": 0.761, "fr": -0.0248, "atr": 3.76, "flow": 1.6, "surge": 1.06, "ret4": 3.35, "bb_pos": 0.752, "bb_squeeze": true, "bb_just_broke": false, "rng": 0.521, "kimp": null, "liq": [6786.732875199999, 339.64924, 19], "vwap_broke": false, "spot_fuel": false, "turnover": 24897001, "tradfi": false, "pinned": true, "rank": 16, "since": 1784377937, "since_min": 78}, {"sym": "SPYUSDT", "base": "SPY", "mark": "🟡", "why": "연료 약함 — 관찰", "alpha": 47, "g": [["흡수/이탈", "— 0", 0], ["VWAP", "VWAP 아래 저항 -4", -4], ["MTF", "BTC 동조화 +0", 0], ["오더북", "매도벽 압박 ×0.58 -8", -8], ["청산", "청산 데이터 없음 0", 0], ["볼밴", "밴드압축 0.3% — 대기 +4", 4], ["스퀴즈", "정상 +0", 0], ["ATR", "극저 변동성 +6", 6], ["레인지", "레인지 내 0", 0], ["FLOW", "Flow +19", 19], ["SURGE", "×0.99 +0", 0], ["KIMCHI", "—", 0]], "conflict": [], "onchain": null, "price": 743.31, "p24": 0.0, "oi4": 2.0, "oi1": 0.8, "cvd": 0.83, "fr": 0.0, "atr": 0.12, "flow": 11.9, "surge": 0.99, "ret4": 0.03, "bb_pos": 0.36, "bb_squeeze": true, "bb_just_broke": false, "rng": 0.329, "kimp": null, "liq": null, "vwap_broke": true, "spot_fuel": false, "turnover": 30439708, "tradfi": true, "pinned": false, "rank": 17, "since": 1784163032, "since_min": 3659}, {"sym": "BUSDT", "base": "B", "mark": "🟡", "why": "연료 약함 — 관찰", "alpha": 45, "g": [["흡수/이탈", "— 0", 0], ["VWAP", "VWAP 아래 저항 -4", -4], ["MTF", "BTC 대비 강세 +6", 6], ["오더북", "균형 ×1.12 +0", 0], ["청산", "혼조 0", 0], ["볼밴", "밴드 중단 0", 0], ["스퀴즈", "정상 +0", 0], ["ATR", "고변동성 -4", -4], ["레인지", "레인지 내 0", 0], ["FLOW", "Flow -1", -1], ["SURGE", "×36.17 +18", 18], ["KIMCHI", "—", 0]], "conflict": [], "onchain": null, "price": 0.144, "p24": 25.98, "oi4": 15.8, "oi1": 0.3, "cvd": 0.403, "fr": 0.0158, "atr": 17.07, "flow": -0.7, "surge": 36.17, "ret4": 3.99, "bb_pos": 0.739, "bb_squeeze": false, "bb_just_broke": false, "rng": 0.423, "kimp": null, "liq": [140673.4267326, 164512.5943218, 534], "vwap_broke": true, "spot_fuel": false, "turnover": 110947086, "tradfi": false, "pinned": false, "rank": 18, "since": 1784380818, "since_min": 30}, {"sym": "PENGUUSDT", "base": "PENGU", "mark": "🟡", "why": "연료 약함 — 관찰", "alpha": 44, "g": [["흡수/이탈", "— 0", 0], ["VWAP", "VWAP 위 지지 +4", 4], ["MTF", "BTC 동조화 +0", 0], ["오더북", "매도벽 압박 ×0.64 -8", -8], ["청산", "미미 $1K 0", 0], ["볼밴", "밴드압축 4.9% — 대기 +4", 4], ["스퀴즈", "FR스퀴즈 중 +5", 5], ["ATR", "낮은 변동성 +3", 3], ["레인지", "레인지 내 0", 0], ["FLOW", "Flow +6", 6], ["SURGE", "×0.67 +0", 0], ["KIMCHI", "+0.19%", 0]], "conflict": [], "onchain": null, "price": 0.005986, "p24": 1.73, "oi4": 2.1, "oi1": 0.3, "cvd": 0.584, "fr": -0.0165, "atr": 1.46, "flow": 3.9, "surge": 0.67, "ret4": 1.41, "bb_pos": 0.506, "bb_squeeze": true, "bb_just_broke": false, "rng": 0.501, "kimp": 0.19, "liq": [506.629588, 1195.520078, 7], "vwap_broke": false, "spot_fuel": false, "turnover": 47152012, "tradfi": false, "pinned": false, "rank": 19, "since": 1784312957, "since_min": 1161}, {"sym": "AAVEUSDT", "base": "AAVE", "mark": "🟡", "why": "연료 약함 — 관찰", "alpha": 43, "g": [["흡수/이탈", "— 0", 0], ["VWAP", "VWAP 위 지지 +4", 4], ["MTF", "BTC 동조화 +0", 0], ["오더북", "균형 ×1.05 +0", 0], ["청산", "미미 $18K 0", 0], ["볼밴", "밴드 중단 0", 0], ["스퀴즈", "정상 +0", 0], ["ATR", "극저 변동성 +6", 6], ["레인지", "레인지 내 0", 0], ["FLOW", "Flow +3", 3], ["SURGE", "×0.87 +0", 0], ["KIMCHI", "-0.08%", 0]], "conflict": [], "onchain": null, "price": 88.1, "p24": -2.54, "oi4": 1.3, "oi1": 0.3, "cvd": 0.754, "fr": 0.0068, "atr": 0.63, "flow": 1.8, "surge": 0.87, "ret4": 0.18, "bb_pos": 0.281, "bb_squeeze": false, "bb_just_broke": false, "rng": 0.163, "kimp": -0.08, "liq": [210.864, 17982.1902, 7], "vwap_broke": false, "spot_fuel": false, "turnover": 62358210, "tradfi": false, "pinned": false, "rank": 20, "since": 1784170952, "since_min": 3527}, {"sym": "DODOXUSDT", "base": "DODOX", "mark": "🟡", "why": "연료 약함 — 관찰", "alpha": 42, "g": [["흡수/이탈", "— 0", 0], ["VWAP", "VWAP 아래 저항 -4", -4], ["MTF", "BTC 동조화 +0", 0], ["오더북", "매수 우위 ×1.28 +4", 4], ["청산", "미미 $12K 0", 0], ["볼밴", "밴드압축 15.2% — 대기 +4", 4], ["스퀴즈", "대형 FR스퀴즈 ★ +8", 8], ["ATR", "정상 변동성 +0", 0], ["레인지", "레인지 내 0", 0], ["FLOW", "Flow +0", 0], ["SURGE", "×1.37 +0", 0], ["KIMCHI", "—", 0]], "conflict": [], "onchain": null, "price": 0.02238, "p24": 11.49, "oi4": 4.1, "oi1": 2.0, "cvd": 0.477, "fr": -0.0554, "atr": 4.99, "flow": 0.1, "surge": 1.37, "ret4": 1.31, "bb_pos": 0.378, "bb_squeeze": true, "bb_just_broke": false, "rng": 0.444, "kimp": null, "liq": [12140.1253378, 8783.585411099999, 40], "vwap_broke": true, "spot_fuel": false, "turnover": 42226206, "tradfi": false, "pinned": false, "rank": 21, "since": 1784381718, "since_min": 15}, {"sym": "ENAUSDT", "base": "ENA", "mark": "🟡", "why": "연료 약함 — 관찰", "alpha": 35, "g": [["흡수/이탈", "— 0", 0], ["VWAP", "VWAP 아래 저항 -4", -4], ["MTF", "BTC 동조화 +0", 0], ["오더북", "매수벽 우위 ×1.90 +8", 8], ["청산", "미미 $1K 0", 0], ["볼밴", "밴드압축 4.2% — 대기 +4", 4], ["스퀴즈", "정상 +0", 0], ["ATR", "극저 변동성 +6", 6], ["레인지", "레인지 내 0", 0], ["FLOW", "Flow -9", -9], ["SURGE", "×1.14 +0", 0], ["KIMCHI", "-0.54%", 0]], "conflict": [], "onchain": null, "price": 0.08022, "p24": 1.06, "oi4": 1.5, "oi1": 0.6, "cvd": 0.731, "fr": -0.0012, "atr": 0.81, "flow": -5.8, "surge": 1.14, "ret4": 0.12, "bb_pos": 0.128, "bb_squeeze": true, "bb_just_broke": false, "rng": 0.213, "kimp": -0.54, "liq": [22.755110000000002, 1479.7602932, 4], "vwap_broke": true, "spot_fuel": false, "turnover": 56273488, "tradfi": false, "pinned": false, "rank": 22, "since": 1784293337, "since_min": 1488}, {"sym": "SNDKUSDT", "base": "SNDK", "mark": "🟡", "why": "연료 약함 — 관찰", "alpha": 34, "g": [["흡수/이탈", "— 0", 0], ["VWAP", "VWAP 위 지지 +4", 4], ["MTF", "BTC 동조화 +0", 0], ["오더북", "매도벽 압박 ×0.59 -8", -8], ["청산", "미미 $5K 0", 0], ["볼밴", "밴드압축 4.8% — 대기 +4", 4], ["스퀴즈", "정상 +0", 0], ["ATR", "극저 변동성 +6", 6], ["레인지", "저점 근접 -6", -6], ["FLOW", "Flow +4", 4], ["SURGE", "×0.71 +0", 0], ["KIMCHI", "—", 0]], "conflict": [], "onchain": null, "price": 1348.04, "p24": -0.59, "oi4": 1.5, "oi1": 0.2, "cvd": 0.476, "fr": 0.0, "atr": 0.44, "flow": 2.5, "surge": 0.71, "ret4": 0.06, "bb_pos": 0.394, "bb_squeeze": true, "bb_just_broke": false, "rng": 0.067, "kimp": null, "liq": [0, 5469.4150957, 5], "vwap_broke": false, "spot_fuel": false, "turnover": 2856393884, "tradfi": true, "pinned": false, "rank": 23, "since": 1784325737, "since_min": 948}, {"sym": "SOLUSDT", "base": "SOL", "mark": "🟡", "why": "연료 약함 — 관찰", "alpha": 33, "g": [["흡수/이탈", "— 0", 0], ["VWAP", "VWAP 아래 저항 -4", -4], ["MTF", "BTC 동조화 +0", 0], ["오더북", "균형 ×1.14 +0", 0], ["청산", "↓ 롱청산 우위 $30K -6", -6], ["볼밴", "밴드압축 0.9% — 대기 +4", 4], ["스퀴즈", "정상 +0", 0], ["ATR", "극저 변동성 +6", 6], ["레인지", "레인지 내 0", 0], ["FLOW", "Flow +3", 3], ["SURGE", "×1.34 +0", 0], ["KIMCHI", "+0.07%", 0]], "conflict": [], "onchain": null, "price": 74.66, "p24": 1.12, "oi4": 0.2, "oi1": 0.0, "cvd": 0.665, "fr": 0.0013, "atr": 0.42, "flow": 2.1, "surge": 1.34, "ret4": -0.19, "bb_pos": -0.049, "bb_squeeze": true, "bb_just_broke": false, "rng": 0.495, "kimp": 0.07, "liq": [17975.6074, 30331.6902, 34], "vwap_broke": true, "spot_fuel": false, "turnover": 662572298, "tradfi": false, "pinned": true, "rank": 24, "since": 1784095877, "since_min": 4779}, {"sym": "SKHYUSDT", "base": "SKHY", "mark": "🟡", "why": "연료 약함 — 관찰", "alpha": 29, "g": [["흡수/이탈", "— 0", 0], ["VWAP", "VWAP 위 지지 +4", 4], ["MTF", "BTC 동조화 +0", 0], ["오더북", "매도벽 압박 ×0.38 -8", -8], ["청산", "청산 데이터 없음 0", 0], ["볼밴", "밴드압축 3.2% — 대기 +4", 4], ["스퀴즈", "정상 +0", 0], ["ATR", "극저 변동성 +6", 6], ["레인지", "저점 근접 -6", -6], ["FLOW", "Flow -1", -1], ["SURGE", "×0.68 +0", 0], ["KIMCHI", "—", 0]], "conflict": [], "onchain": null, "price": 153.43, "p24": 2.08, "oi4": 1.4, "oi1": 0.2, "cvd": 0.631, "fr": 0.0, "atr": 0.46, "flow": -0.9, "surge": 0.68, "ret4": -0.04, "bb_pos": 0.356, "bb_squeeze": true, "bb_just_broke": false, "rng": 0.067, "kimp": null, "liq": null, "vwap_broke": false, "spot_fuel": false, "turnover": 1013159639, "tradfi": false, "pinned": false, "rank": 25, "since": 1784316917, "since_min": 1095}, {"sym": "SOXLUSDT", "base": "SOXL", "mark": "🟡", "why": "연료 약함 — 관찰", "alpha": 29, "g": [["흡수/이탈", "— 0", 0], ["VWAP", "VWAP 위 지지 +4", 4], ["MTF", "BTC 동조화 +0", 0], ["오더북", "매도 우위 ×0.86 -4", -4], ["청산", "미미 $8K 0", 0], ["볼밴", "밴드압축 3.4% — 대기 +4", 4], ["스퀴즈", "정상 +0", 0], ["ATR", "극저 변동성 +6", 6], ["레인지", "레인지 내 0", 0], ["FLOW", "Flow -11", -11], ["SURGE", "×0.85 +0", 0], ["KIMCHI", "—", 0]], "conflict": [], "onchain": null, "price": 133.74, "p24": 10.03, "oi4": 1.1, "oi1": 0.1, "cvd": 0.681, "fr": 0.0, "atr": 0.93, "flow": -6.9, "surge": 0.85, "ret4": 0.79, "bb_pos": 0.447, "bb_squeeze": true, "bb_just_broke": false, "rng": 0.376, "kimp": null, "liq": [5205.702022, 8334.808516000001, 8], "vwap_broke": false, "spot_fuel": false, "turnover": 1766504835, "tradfi": true, "pinned": false, "rank": 26, "since": 1784302157, "since_min": 1341}, {"sym": "ETHUSDT", "base": "ETH", "mark": "🟡", "why": "연료 약함 — 관찰", "alpha": 25, "g": [["흡수/이탈", "— 0", 0], ["VWAP", "VWAP 아래 저항 -4", -4], ["MTF", "BTC 동조화 +0", 0], ["오더북", "매도벽 압박 ×0.26 -8", -8], ["청산", "↓ 롱청산 우위 $176K -6", -6], ["볼밴", "밴드압축 0.5% — 대기 +4", 4], ["스퀴즈", "정상 +0", 0], ["ATR", "극저 변동성 +6", 6], ["레인지", "레인지 상단 +6", 6], ["FLOW", "Flow -7", -7], ["SURGE", "×1.41 +4", 4], ["KIMCHI", "+0.05%", 0]], "conflict": [], "onchain": null, "price": 1840.25, "p24": 1.5, "oi4": 0.1, "oi1": -0.1, "cvd": 0.13, "fr": 0.0038, "atr": 0.33, "flow": -4.5, "surge": 1.41, "ret4": -0.18, "bb_pos": 0.226, "bb_squeeze": true, "bb_just_broke": false, "rng": 0.676, "kimp": 0.05, "liq": [117101.78671, 176025.33836999998, 65], "vwap_broke": true, "spot_fuel": false, "turnover": 3990162416, "tradfi": false, "pinned": true, "rank": 27, "since": 1784203517, "since_min": 2985}, {"sym": "APTUSDT", "base": "APT", "mark": "🟡", "why": "연료 약함 — 관찰", "alpha": 23, "g": [["흡수/이탈", "— 0", 0], ["VWAP", "VWAP 아래 저항 -4", -4], ["MTF", "BTC 동조화 +0", 0], ["오더북", "균형 ×0.96 +0", 0], ["청산", "미미 $3K 0", 0], ["볼밴", "밴드압축 3.6% — 대기 +4", 4], ["스퀴즈", "정상 +0", 0], ["ATR", "극저 변동성 +6", 6], ["레인지", "레인지 내 0", 0], ["FLOW", "Flow -17", -17], ["SURGE", "×1.75 +4", 4], ["KIMCHI", "+0.16%", 0]], "conflict": [], "onchain": null, "price": 0.6035, "p24": 1.45, "oi4": 1.6, "oi1": 0.8, "cvd": 0.153, "fr": 0.0034, "atr": 0.73, "flow": -10.5, "surge": 1.75, "ret4": -0.74, "bb_pos": 0.009, "bb_squeeze": true, "bb_just_broke": false, "rng": 0.239, "kimp": 0.16, "liq": [0, 3039.524824, 2], "vwap_broke": true, "spot_fuel": false, "turnover": 15426587, "tradfi": false, "pinned": false, "rank": 28, "since": 1784379737, "since_min": 48}, {"sym": "REUSDT", "base": "RE", "mark": "🟡", "why": "연료 약함 — 관찰", "alpha": 15, "g": [["흡수/이탈", "— 0", 0], ["VWAP", "VWAP 아래 저항 -4", -4], ["MTF", "BTC 동조화 +0", 0], ["오더북", "균형 ×1.01 +0", 0], ["청산", "미미 $19K 0", 0], ["볼밴", "밴드 하단 -3", -3], ["스퀴즈", "대형 FR스퀴즈 ★ +8", 8], ["ATR", "정상 변동성 +0", 0], ["레인지", "저점 근접 -6", -6], ["FLOW", "Flow -10", -10], ["SURGE", "×0.88 +0", 0], ["KIMCHI", "+0.77%", 0]], "conflict": [], "onchain": null, "price": 0.3979, "p24": -9.75, "oi4": 4.1, "oi1": 0.8, "cvd": 0.484, "fr": -0.1075, "atr": 2.68, "flow": -6.5, "surge": 0.88, "ret4": -1.85, "bb_pos": 0.107, "bb_squeeze": false, "bb_just_broke": false, "rng": 0.053, "kimp": 0.77, "liq": [4252.4478424, 19376.1075136, 38], "vwap_broke": true, "spot_fuel": false, "turnover": 36669782, "tradfi": false, "pinned": false, "rank": 29, "since": 1784382618, "since_min": 0}, {"sym": "VVVUSDT", "base": "VVV", "mark": "🟡", "why": "연료 약함 — 관찰", "alpha": 15, "g": [["흡수/이탈", "— 0", 0], ["VWAP", "VWAP 아래 저항 -4", -4], ["MTF", "BTC 동조화 +0", 0], ["오더북", "매도벽 압박 ×0.63 -8", -8], ["청산", "미미 $9K 0", 0], ["볼밴", "밴드압축 7.0% — 대기 +4", 4], ["스퀴즈", "정상 +0", 0], ["ATR", "정상 변동성 +0", 0], ["레인지", "레인지 상단 +6", 6], ["FLOW", "Flow -13", -13], ["SURGE", "×1.08 +0", 0], ["KIMCHI", "+0.21%", 0]], "conflict": [], "onchain": null, "price": 11.41, "p24": 15.26, "oi4": 1.3, "oi1": -0.6, "cvd": 0.198, "fr": 0.005, "atr": 2.06, "flow": -8.2, "surge": 1.08, "ret4": -1.67, "bb_pos": 0.549, "bb_squeeze": true, "bb_just_broke": false, "rng": 0.788, "kimp": 0.21, "liq": [509.26937065000004, 8787.73236789, 19], "vwap_broke": true, "spot_fuel": false, "turnover": 33469566, "tradfi": false, "pinned": false, "rank": 30, "since": 1784307737, "since_min": 1248}, {"sym": "1000PEPEUSDT", "base": "PEPE", "mark": "🟡", "why": "연료 약함 — 관찰", "alpha": 14, "g": [["흡수/이탈", "— 0", 0], ["VWAP", "VWAP 아래 저항 -4", -4], ["MTF", "BTC 동조화 +0", 0], ["오더북", "매도벽 압박 ×0.56 -8", -8], ["청산", "미미 $3K 0", 0], ["볼밴", "밴드압축 1.6% — 대기 +4", 4], ["스퀴즈", "정상 +0", 0], ["ATR", "극저 변동성 +6", 6], ["레인지", "레인지 내 0", 0], ["FLOW", "Flow -14", -14], ["SURGE", "×1.25 +0", 0], ["KIMCHI", "-99.90%", 0]], "conflict": [], "onchain": null, "price": 0.0027237, "p24": 1.49, "oi4": 1.8, "oi1": 0.3, "cvd": 0.567, "fr": 0.01, "atr": 0.66, "flow": -8.7, "surge": 1.25, "ret4": 0.26, "bb_pos": 0.274, "bb_squeeze": true, "bb_just_broke": false, "rng": 0.575, "kimp": -99.9, "liq": [2823.9862768000003, 1740.7775386, 8], "vwap_broke": true, "spot_fuel": false, "turnover": 85818161, "tradfi": false, "pinned": false, "rank": 31, "since": 1784187691, "since_min": 3248}, {"sym": "FILUSDT", "base": "FIL", "mark": "🟡", "why": "연료 약함 — 관찰", "alpha": 4, "g": [["흡수/이탈", "— 0", 0], ["VWAP", "VWAP 아래 저항 -4", -4], ["MTF", "BTC 동조화 +0", 0], ["오더북", "매도 우위 ×0.73 -4", -4], ["청산", "↓ 롱청산 우위 $63K -6", -6], ["볼밴", "밴드 하단 -3", -3], ["스퀴즈", "정상 +0", 0], ["ATR", "낮은 변동성 +3", 3], ["레인지", "레인지 내 0", 0], ["FLOW", "Flow -30", -30], ["SURGE", "×3.16 +18", 18], ["KIMCHI", "+0.04%", 0]], "conflict": [], "onchain": null, "price": 0.7421, "p24": -1.99, "oi4": 1.1, "oi1": 0.4, "cvd": 0.125, "fr": -0.0011, "atr": 1.11, "flow": -20.2, "surge": 3.16, "ret4": -1.64, "bb_pos": -0.216, "bb_squeeze": false, "bb_just_broke": false, "rng": 0.196, "kimp": 0.04, "liq": [0, 62801.7660656, 11], "vwap_broke": true, "spot_fuel": false, "turnover": 26515761, "tradfi": false, "pinned": false, "rank": 32, "since": 1784293517, "since_min": 1485}, {"sym": "SLXUSDT", "base": "SLX", "mark": "🟡", "why": "연료 약함 — 관찰", "alpha": 3, "g": [["흡수/이탈", "— 0", 0], ["VWAP", "VWAP 아래 저항 -4", -4], ["MTF", "BTC 동조화 +0", 0], ["오더북", "매수벽 우위 ×1.79 +8", 8], ["청산", "미미 $11K 0", 0], ["볼밴", "밴드 하단 -3", -3], ["스퀴즈", "FR스퀴즈 중 +5", 5], ["ATR", "낮은 변동성 +3", 3], ["레인지", "저점 근접 -6", -6], ["FLOW", "Flow -30", -30], ["SURGE", "×0.93 +0", 0], ["KIMCHI", "+0.12%", 0]], "conflict": [], "onchain": null, "price": 0.10738, "p24": -9.85, "oi4": 1.5, "oi1": 1.8, "cvd": 0.198, "fr": -0.0256, "atr": 1.62, "flow": -23.0, "surge": 0.93, "ret4": -2.23, "bb_pos": 0.152, "bb_squeeze": false, "bb_just_broke": false, "rng": 0.038, "kimp": 0.12, "liq": [0, 11050.5525438, 17], "vwap_broke": true, "spot_fuel": false, "turnover": 17269113, "tradfi": false, "pinned": false, "rank": 33, "since": 1784199556, "since_min": 3051}, {"sym": "HOMEUSDT", "base": "HOME", "mark": "🔴", "why": "하락 중 -17% — 롱 근거 없음", "alpha": 37, "g": [["흡수/이탈", "— 0", 0], ["VWAP", "VWAP 위 지지 +4", 4], ["MTF", "BTC 동조화 +0", 0], ["오더북", "균형 ×1.06 +0", 0], ["청산", "미미 $28K 0", 0], ["볼밴", "밴드 중단 0", 0], ["스퀴즈", "대형 FR스퀴즈 ★ +8", 8], ["ATR", "정상 변동성 +0", 0], ["레인지", "레인지 내 0", 0], ["FLOW", "Flow -5", -5], ["SURGE", "×0.56 +0", 0], ["KIMCHI", "—", 0]], "conflict": [], "onchain": null, "price": 0.00672, "p24": -16.93, "oi4": 4.5, "oi1": -0.9, "cvd": 0.702, "fr": -1.2112, "atr": 3.26, "flow": -3.4, "surge": 0.56, "ret4": -0.59, "bb_pos": 0.223, "bb_squeeze": false, "bb_just_broke": false, "rng": 0.122, "kimp": null, "liq": [8072.7009, 28215.344069, 69], "vwap_broke": false, "spot_fuel": false, "turnover": 86528271, "tradfi": false, "pinned": false, "rank": 34, "since": 1784368398, "since_min": 236}, {"sym": "ARXUSDT", "base": "ARX", "mark": "🔴", "why": "하락 중 -13% — 롱 근거 없음", "alpha": 27, "g": [["흡수/이탈", "— 0", 0], ["VWAP", "VWAP 아래 저항 -4", -4], ["MTF", "BTC 동조화 +0", 0], ["오더북", "균형 ×0.89 +0", 0], ["청산", "미미 $9K 0", 0], ["볼밴", "밴드 중단 0", 0], ["스퀴즈", "대형 FR스퀴즈 ★ +8", 8], ["ATR", "낮은 변동성 +3", 3], ["레인지", "저점 근접 -6", -6], ["FLOW", "Flow -4", -4], ["SURGE", "×0.68 +0", 0], ["KIMCHI", "+0.34%", 0]], "conflict": [], "onchain": null, "price": 0.1496, "p24": -13.18, "oi4": 3.7, "oi1": 0.9, "cvd": 0.832, "fr": -0.0589, "atr": 1.88, "flow": -2.7, "surge": 0.68, "ret4": 0.74, "bb_pos": 0.213, "bb_squeeze": false, "bb_just_broke": false, "rng": 0.069, "kimp": 0.34, "liq": [85.1697, 8804.061996999999, 9], "vwap_broke": true, "spot_fuel": false, "turnover": 23249459, "tradfi": false, "pinned": false, "rank": 35, "since": 1784375057, "since_min": 126}]}